{
    "transactionid": "LBS_29027059",
    "status": 0,
    "illist": [
        { "id": 1, "name": "ADANA", "latitude": 37.00039, "longitude": 35.31411, "extent": { "minlatitude": 36.54294597, "minlongitude": 34.76786904, "maxlatitude": 38.37851496, "maxlongitude": 36.40534884 } },
        { "id": 2, "name": "ADIYAMAN", "latitude": 37.76454, "longitude": 38.27645, "extent": { "minlatitude": 37.40771898, "minlongitude": 37.43326512, "maxlatitude": 38.21203404, "maxlongitude": 39.24767592 } },
        { "id": 3, "name": "AFYONKARAHİSAR", "latitude": 38.75754, "longitude": 30.5387, "extent": { "minlatitude": 37.78126803, "minlongitude": 29.68963308, "maxlatitude": 39.27915099, "maxlongitude": 31.71549708 } },
        { "id": 4, "name": "AĞRI", "latitude": 39.71812, "longitude": 43.03345, "extent": { "minlatitude": 38.96877501, "minlongitude": 42.28340184, "maxlatitude": 40.031208, "maxlongitude": 44.61092892 } },
        { "id": 68, "name": "AKSARAY", "latitude": 38.37374, "longitude": 34.02934, "extent": { "minlatitude": 37.97195904, "minlongitude": 33.17666292, "maxlatitude": 39.05478297, "maxlongitude": 34.49033316 } },
        { "id": 5, "name": "AMASYA", "latitude": 40.65367, "longitude": 35.83362, "extent": { "minlatitude": 40.23363501, "minlongitude": 34.99334316, "maxlatitude": 41.08958001, "maxlongitude": 36.49172292 } },
        { "id": 6, "name": "ANKARA", "latitude": 39.94415, "longitude": 32.8563, "extent": { "minlatitude": 38.63962296, "minlongitude": 30.80234196, "maxlatitude": 40.71930201, "maxlongitude": 33.93751716 } },
        { "id": 7, "name": "ANTALYA", "latitude": 36.88742, "longitude": 30.70321, "extent": { "minlatitude": 36.09240696, "minlongitude": 29.28344904, "maxlatitude": 37.42004898, "maxlongitude": 32.62997484 } },
        { "id": 75, "name": "ARDAHAN", "latitude": 41.11094, "longitude": 42.6982, "extent": { "minlatitude": 40.63215303, "minlongitude": 42.32584584, "maxlatitude": 41.60090502, "maxlongitude": 43.47434016 } },
        { "id": 8, "name": "ARTVİN", "latitude": 41.18113, "longitude": 41.82037, "extent": { "minlatitude": 40.56144903, "minlongitude": 41.15523096, "maxlatitude": 41.52482901, "maxlongitude": 42.59433096 } },
        { "id": 9, "name": "AYDIN", "latitude": 37.85351, "longitude": 27.84381, "extent": { "minlatitude": 37.335852, "minlongitude": 27.00564084, "maxlatitude": 38.11704597, "maxlongitude": 28.86455088 } },
        { "id": 10, "name": "BALIKESİR", "latitude": 39.64538, "longitude": 27.88374, "extent": { "minlatitude": 39.05219799, "minlongitude": 26.56012104, "maxlatitude": 40.66701696, "maxlongitude": 28.99689192 } },
        { "id": 74, "name": "BARTIN", "latitude": 41.63279, "longitude": 32.3365, "extent": { "minlatitude": 41.28713901, "minlongitude": 32.07336192, "maxlatitude": 41.84821098, "maxlongitude": 32.91424308 } },
        { "id": 72, "name": "BATMAN", "latitude": 37.89991, "longitude": 41.12921, "extent": { "minlatitude": 37.49873796, "minlongitude": 40.99361004, "maxlatitude": 38.56726503, "maxlongitude": 41.73018192 } },
        { "id": 69, "name": "BAYBURT", "latitude": 40.25924, "longitude": 40.22645, "extent": { "minlatitude": 39.92031297, "minlongitude": 39.65769612, "maxlatitude": 40.571505, "maxlongitude": 40.75492392 } },
        { "id": 11, "name": "BİLECİK", "latitude": 40.14469, "longitude": 29.98206, "extent": { "minlatitude": 39.65094, "minlongitude": 29.70607896, "maxlatitude": 40.51197801, "maxlongitude": 30.66025212 } },
        { "id": 12, "name": "BİNGÖL", "latitude": 38.88431, "longitude": 40.49625, "extent": { "minlatitude": 38.46418704, "minlongitude": 39.90686904, "maxlatitude": 39.55524498, "maxlongitude": 41.30965908 } },
        { "id": 13, "name": "BİTLİS", "latitude": 38.40608, "longitude": 42.10616, "extent": { "minlatitude": 37.97970597, "minlongitude": 41.51139588, "maxlatitude": 39.02442498, "maxlongitude": 43.225983 } },
        { "id": 14, "name": "BOLU", "latitude": 40.73019, "longitude": 31.60021, "extent": { "minlatitude": 40.13143803, "minlongitude": 30.55315392, "maxlatitude": 41.03312598, "maxlongitude": 32.61191112 } },
        { "id": 15, "name": "BURDUR", "latitude": 37.71875, "longitude": 30.2825, "extent": { "minlatitude": 36.85271904, "minlongitude": 29.333808, "maxlatitude": 37.83361698, "maxlongitude": 30.90988116 } },
        { "id": 16, "name": "BURSA", "latitude": 40.18282, "longitude": 29.06604, "extent": { "minlatitude": 39.58329699, "minlongitude": 28.08373896, "maxlatitude": 40.61347398, "maxlongitude": 29.93104008 } },
        { "id": 17, "name": "ÇANAKKALE", "latitude": 40.15156, "longitude": 26.40569, "extent": { "minlatitude": 39.45330603, "minlongitude": 25.66850904, "maxlatitude": 40.73945301, "maxlongitude": 27.53091684 } },
        { "id": 18, "name": "ÇANKIRI", "latitude": 40.5994, "longitude": 33.61662, "extent": { "minlatitude": 40.25488302, "minlongitude": 32.57693784, "maxlatitude": 41.07607398, "maxlongitude": 34.16334516 } },
        { "id": 19, "name": "ÇORUM", "latitude": 40.55275, "longitude": 34.95942, "extent": { "minlatitude": 39.93370299, "minlongitude": 33.94952208, "maxlatitude": 41.32847097, "maxlongitude": 35.52452604 } },
        { "id": 20, "name": "DENİZLİ", "latitude": 37.78069, "longitude": 29.085, "extent": { "minlatitude": 36.85021497, "minlongitude": 28.60244496, "maxlatitude": 38.48244498, "maxlongitude": 30.11215896 } },
        { "id": 21, "name": "DİYARBAKIR", "latitude": 37.91625, "longitude": 40.22559, "extent": { "minlatitude": 37.50389001, "minlongitude": 39.09461508, "maxlatitude": 38.71651698, "maxlongitude": 41.38687188 } },
        { "id": 81, "name": "DÜZCE", "latitude": 40.84, "longitude": 31.15506, "extent": { "minlatitude": 40.61723598, "minlongitude": 30.82073508, "maxlatitude": 41.11800399, "maxlongitude": 31.76339688 } },
        { "id": 22, "name": "EDİRNE", "latitude": 41.6791, "longitude": 26.55161, "extent": { "minlatitude": 40.59036702, "minlongitude": 26.035038, "maxlatitude": 42.00195402, "maxlongitude": 26.993457 } },
        { "id": 23, "name": "ELAZIĞ", "latitude": 38.67217, "longitude": 39.19462, "extent": { "minlatitude": 38.26462797, "minlongitude": 38.35605096, "maxlatitude": 39.17685897, "maxlongitude": 40.34464992 } },
        { "id": 24, "name": "ERZİNCAN", "latitude": 39.75181, "longitude": 39.49093, "extent": { "minlatitude": 39.01578003, "minlongitude": 38.26074492, "maxlatitude": 40.075263, "maxlongitude": 40.77064188 } },
        { "id": 25, "name": "ERZURUM", "latitude": 39.90375, "longitude": 41.26219, "extent": { "minlatitude": 39.14941401, "minlongitude": 40.25411316, "maxlatitude": 40.95286101, "maxlongitude": 42.57652608 } },
        { "id": 26, "name": "ESKİŞEHİR", "latitude": 39.77078, "longitude": 30.51798, "extent": { "minlatitude": 39.07212597, "minlongitude": 30.00324888, "maxlatitude": 40.15295604, "maxlongitude": 32.03645184 } },
        { "id": 27, "name": "GAZİANTEP", "latitude": 37.06584, "longitude": 37.37608, "extent": { "minlatitude": 36.70290999, "minlongitude": 36.46486296, "maxlatitude": 37.53411003, "maxlongitude": 38.077119 } },
        { "id": 28, "name": "GİRESUN", "latitude": 40.92154, "longitude": 38.38693, "extent": { "minlatitude": 40.03852401, "minlongitude": 37.95267888, "maxlatitude": 41.08122, "maxlongitude": 39.17858112 } },
        { "id": 29, "name": "GÜMÜŞHANE", "latitude": 40.45992, "longitude": 39.48069, "extent": { "minlatitude": 39.84137397, "minlongitude": 38.78306208, "maxlatitude": 40.83384996, "maxlongitude": 40.14597708 } },
        { "id": 30, "name": "HAKKARİ", "latitude": 37.57835, "longitude": 43.73819, "extent": { "minlatitude": 36.963459, "minlongitude": 43.30785096, "maxlatitude": 37.80946404, "maxlongitude": 44.81793108 } },
        { "id": 31, "name": "HATAY", "latitude": 36.19824, "longitude": 36.15931, "extent": { "minlatitude": 35.80842798, "minlongitude": 35.78209596, "maxlatitude": 37.01148003, "maxlongitude": 36.697815 } },
        { "id": 76, "name": "IĞDIR", "latitude": 39.92375, "longitude": 44.04635, "extent": { "minlatitude": 39.62774799, "minlongitude": 43.28039304, "maxlatitude": 40.15740096, "maxlongitude": 44.81775216 } },
        { "id": 32, "name": "ISPARTA", "latitude": 37.76434, "longitude": 30.55621, "extent": { "minlatitude": 37.30922496, "minlongitude": 30.04243308, "maxlatitude": 38.51573103, "maxlongitude": 31.58005284 } },
        { "id": 34, "name": "İSTANBUL", "latitude": 41.01238, "longitude": 28.97596, "extent": { "minlatitude": 40.80273399, "minlongitude": 27.971307, "maxlatitude": 41.58383004, "maxlongitude": 29.95864416 } },
        { "id": 342, "name": "İSTANBUL ANADOLU YAKASI", "latitude": 40.9896, "longitude": 29.0641, "extent": { "minlatitude": 40.80273399, "minlongitude": 29.00628684, "maxlatitude": 41.23521504, "maxlongitude": 29.95864416 } },
        { "id": 341, "name": "İSTANBUL AVRUPA YAKASI", "latitude": 41.00851, "longitude": 28.97369, "extent": { "minlatitude": 40.954536, "minlongitude": 27.971307, "maxlatitude": 41.583825, "maxlongitude": 29.11613616 } },
        { "id": 35, "name": "İZMİR", "latitude": 38.41872, "longitude": 27.1296, "extent": { "minlatitude": 37.83570903, "minlongitude": 26.20560204, "maxlatitude": 39.38588001, "maxlongitude": 28.49982696 } },
        { "id": 46, "name": "KAHRAMANMARAŞ", "latitude": 37.5797, "longitude": 36.92951, "extent": { "minlatitude": 37.16680797, "minlongitude": 36.024732, "maxlatitude": 38.57840496, "maxlongitude": 37.74927816 } },
        { "id": 78, "name": "KARABÜK", "latitude": 41.19576, "longitude": 32.62171, "extent": { "minlatitude": 40.81611402, "minlongitude": 32.10541704, "maxlatitude": 41.58549, "maxlongitude": 33.15346488 } },
        { "id": 70, "name": "KARAMAN", "latitude": 37.17005, "longitude": 33.22209, "extent": { "minlatitude": 36.377739, "minlongitude": 32.41068516, "maxlatitude": 37.61912403, "maxlongitude": 34.25315004 } },
        { "id": 36, "name": "KARS", "latitude": 40.60041, "longitude": 43.09501, "extent": { "minlatitude": 39.92412798, "minlongitude": 42.12903708, "maxlatitude": 41.11985403, "maxlongitude": 43.75004184 } },
        { "id": 37, "name": "KASTAMONU", "latitude": 41.37583, "longitude": 33.77862, "extent": { "minlatitude": 40.82510403, "minlongitude": 32.72202504, "maxlatitude": 42.01986897, "maxlongitude": 34.605153 } },
        { "id": 38, "name": "KAYSERİ", "latitude": 38.72279, "longitude": 35.48904, "extent": { "minlatitude": 37.713141, "minlongitude": 34.88612508, "maxlatitude": 39.30166701, "maxlongitude": 36.98700804 } },
        { "id": 71, "name": "KIRIKKALE", "latitude": 39.8395, "longitude": 33.50335, "extent": { "minlatitude": 39.41246196, "minlongitude": 33.22240488, "maxlatitude": 40.338666, "maxlongitude": 34.24470984 } },
        { "id": 39, "name": "KIRKLARELİ", "latitude": 41.73396, "longitude": 27.21863, "extent": { "minlatitude": 41.22242901, "minlongitude": 26.87577084, "maxlatitude": 42.10478397, "maxlongitude": 28.14681492 } },
        { "id": 40, "name": "KIRŞEHİR", "latitude": 39.15013, "longitude": 34.16025, "extent": { "minlatitude": 38.80243998, "minlongitude": 33.41347704, "maxlatitude": 39.80090403, "maxlongitude": 34.69862196 } },
        { "id": 79, "name": "KİLİS", "latitude": 36.7216, "longitude": 37.09218, "extent": { "minlatitude": 36.632106, "minlongitude": 36.71842104, "maxlatitude": 37.02860703, "maxlongitude": 37.56675384 } },
        { "id": 41, "name": "KOCAELİ", "latitude": 40.76482, "longitude": 29.93911, "extent": { "minlatitude": 40.51032696, "minlongitude": 29.33302896, "maxlatitude": 41.209848, "maxlongitude": 30.37095216 } },
        { "id": 42, "name": "KONYA", "latitude": 37.87166, "longitude": 32.49896, "extent": { "minlatitude": 36.75940398, "minlongitude": 31.23677412, "maxlatitude": 39.31071399, "maxlongitude": 34.444854 } },
        { "id": 101, "name": "KUZEY KIBRIS TÜRK CUMHURİYETİ", "latitude": 35.21408, "longitude": 33.4896, "extent": { "minlatitude": 35.00447202, "minlongitude": 32.59442304, "maxlatitude": 35.701542, "maxlongitude": 34.59792312 } },
        { "id": 43, "name": "KÜTAHYA", "latitude": 39.41989, "longitude": 29.98519, "extent": { "minlatitude": 38.79995796, "minlongitude": 28.61798184, "maxlatitude": 39.85750404, "maxlongitude": 30.43263492 } },
        { "id": 44, "name": "MALATYA", "latitude": 38.34834, "longitude": 38.31857, "extent": { "minlatitude": 37.89560097, "minlongitude": 37.263591, "maxlatitude": 39.14378703, "maxlongitude": 39.15272916 } },
        { "id": 45, "name": "MANİSA", "latitude": 38.61706, "longitude": 27.43381, "extent": { "minlatitude": 38.07895203, "minlongitude": 27.09859212, "maxlatitude": 39.40906896, "maxlongitude": 29.11309596 } },
        { "id": 47, "name": "MARDİN", "latitude": 37.32477, "longitude": 40.72239, "extent": { "minlatitude": 36.91429398, "minlongitude": 39.915243, "maxlatitude": 37.74159801, "maxlongitude": 41.89885308 } },
        { "id": 33, "name": "MERSİN", "latitude": 36.7997, "longitude": 34.63233, "extent": { "minlatitude": 36.02003697, "minlongitude": 32.56485984, "maxlatitude": 37.43590104, "maxlongitude": 35.15736996 } },
        { "id": 48, "name": "MUĞLA", "latitude": 37.21512, "longitude": 28.36273, "extent": { "minlatitude": 36.27852804, "minlongitude": 27.19655496, "maxlatitude": 37.55792898, "maxlongitude": 29.80946412 } },
        { "id": 49, "name": "MUŞ", "latitude": 38.74655, "longitude": 41.49952, "extent": { "minlatitude": 38.48379804, "minlongitude": 41.11163604, "maxlatitude": 39.50096796, "maxlongitude": 42.74216388 } },
        { "id": 50, "name": "NEVŞEHİR", "latitude": 38.62676, "longitude": 34.72062, "extent": { "minlatitude": 38.32385796, "minlongitude": 34.21378404, "maxlatitude": 39.42218799, "maxlongitude": 35.099109 } },
        { "id": 51, "name": "NİĞDE", "latitude": 37.97023, "longitude": 34.67631, "extent": { "minlatitude": 37.323918, "minlongitude": 33.98683212, "maxlatitude": 38.36162898, "maxlongitude": 35.32314204 } },
        { "id": 52, "name": "ORDU", "latitude": 40.98462, "longitude": 37.87475, "extent": { "minlatitude": 40.31658297, "minlongitude": 36.68901516, "maxlatitude": 41.14813302, "maxlongitude": 38.18741112 } },
        { "id": 80, "name": "OSMANİYE", "latitude": 37.07465, "longitude": 36.24512, "extent": { "minlatitude": 36.911115, "minlongitude": 35.89171812, "maxlatitude": 37.72119096, "maxlongitude": 36.702765 } },
        { "id": 53, "name": "RİZE", "latitude": 41.02864, "longitude": 40.51573, "extent": { "minlatitude": 40.51414503, "minlongitude": 40.33032984, "maxlatitude": 41.32746801, "maxlongitude": 41.43781908 } },
        { "id": 54, "name": "SAKARYA", "latitude": 40.85326, "longitude": 30.31672, "extent": { "minlatitude": 40.29164496, "minlongitude": 29.96723592, "maxlatitude": 41.18428998, "maxlongitude": 31.01715216 } },
        { "id": 55, "name": "SAMSUN", "latitude": 41.28945, "longitude": 36.33928, "extent": { "minlatitude": 40.83051402, "minlongitude": 34.88601312, "maxlatitude": 41.73710796, "maxlongitude": 37.17515988 } },
        { "id": 56, "name": "SİİRT", "latitude": 37.93014, "longitude": 41.94022, "extent": { "minlatitude": 37.56391596, "minlongitude": 41.38122708, "maxlatitude": 38.25294399, "maxlongitude": 42.89671404 } },
        { "id": 57, "name": "SİNOP", "latitude": 42.02687, "longitude": 35.15176, "extent": { "minlatitude": 41.208327, "minlongitude": 34.22949804, "maxlatitude": 42.09800499, "maxlongitude": 35.46764784 } },
        { "id": 58, "name": "SİVAS", "latitude": 39.75097, "longitude": 37.01526, "extent": { "minlatitude": 38.54410497, "minlongitude": 35.84588292, "maxlatitude": 40.50422604, "maxlongitude": 38.78551584 } },
        { "id": 63, "name": "ŞANLIURFA", "latitude": 37.16022, "longitude": 38.79181, "extent": { "minlatitude": 36.66890799, "minlongitude": 37.83235788, "maxlatitude": 38.02822101, "maxlongitude": 40.23739584 } },
        { "id": 73, "name": "ŞIRNAK", "latitude": 37.52271, "longitude": 42.45581, "extent": { "minlatitude": 37.106631, "minlongitude": 41.561811, "maxlatitude": 37.78462296, "maxlongitude": 43.50219012 } },
        { "id": 59, "name": "TEKİRDAĞ", "latitude": 40.97893, "longitude": 27.51524, "extent": { "minlatitude": 40.55619303, "minlongitude": 26.67455784, "maxlatitude": 41.55635898, "maxlongitude": 28.12233312 } },
        { "id": 60, "name": "TOKAT", "latitude": 40.31392, "longitude": 36.55246, "extent": { "minlatitude": 39.88857204, "minlongitude": 35.451009, "maxlatitude": 40.90777101, "maxlongitude": 37.63686204 } },
        { "id": 61, "name": "TRABZON", "latitude": 41.00601, "longitude": 39.71161, "extent": { "minlatitude": 40.52235798, "minlongitude": 39.12806412, "maxlatitude": 41.10983496, "maxlongitude": 40.49490312 } },
        { "id": 62, "name": "TUNCELİ", "latitude": 39.07559, "longitude": 39.53459, "extent": { "minlatitude": 38.76580197, "minlongitude": 38.72891196, "maxlatitude": 39.62336598, "maxlongitude": 40.407219 } },
        { "id": 64, "name": "UŞAK", "latitude": 38.67376, "longitude": 29.40487, "extent": { "minlatitude": 38.18003499, "minlongitude": 28.78086096, "maxlatitude": 38.94946497, "maxlongitude": 30.03870204 } },
        { "id": 65, "name": "VAN", "latitude": 38.50349, "longitude": 43.39645, "extent": { "minlatitude": 37.72198998, "minlongitude": 42.65472708, "maxlatitude": 39.40103502, "maxlongitude": 44.51187492 } },
        { "id": 77, "name": "YALOVA", "latitude": 40.65838, "longitude": 29.2731, "extent": { "minlatitude": 40.455135, "minlongitude": 28.77953292, "maxlatitude": 40.750227, "maxlongitude": 29.563677 } },
        { "id": 66, "name": "YOZGAT", "latitude": 39.82373, "longitude": 34.80784, "extent": { "minlatitude": 38.95935399, "minlongitude": 34.03937484, "maxlatitude": 40.24831698, "maxlongitude": 36.16144416 } },
        { "id": 100, "name": "YURT DIŞI", "latitude": 48.5948, "longitude": 35.91628, "extent": { "minlatitude": 19.30910202, "minlongitude": -2.88784296, "maxlatitude": 60.73654698, "maxlongitude": 62.22643308 } },
        { "id": 67, "name": "ZONGULDAK", "latitude": 41.45519, "longitude": 31.7879, "extent": { "minlatitude": 41.01110001, "minlongitude": 31.29059808, "maxlatitude": 41.58679302, "maxlongitude": 32.330511 } }
    ]
}
